{
	"schemaVersion": 1,
	"id": "rafaels-loot-bundle",
	"version": "${version}",
	"name": "Rafael's Loot Bundles",
	"description": "Adds a fun and randomized loot system to Minecraft!",
	"authors": [
		"RaFaEL0 (Rafael)",
		"Meronia"
	],
	"contact": {
		"sources": "https://github.com/rafaelmehdiyev/Loot-Bundles-Mod"
	},
	"license": "MIT",
	"icon": "assets/rafaels-loot-bundles/icon.png",
	"environment": "*",
	"entrypoints": {
		"main": [
			"net.rafael.lootbundles.RafaelsLootBundles"
		],
		"fabric-datagen": [
			"net.rafael.lootbundles.RafaelsLootBundlesDataGenerator"
		],
		"client": [
			"net.rafael.lootbundles.LootBundleClient"
		]
	},
	"mixins": [
		"rafaels-loot-bundle.mixins.json"
	],
	"depends": {
		"fabricloader": ">=0.16.9",
		"minecraft": "~1.21.3",
		"java": ">=21",
		"fabric-api": "*"
	},
	"suggests": {
		"another-mod": "*"
	}
}